{
  "entries": [
    {
      "payDate": "",
      "id": "1700000012",
      "type": "income",
      "notes": "נשלחה חשבונית עסקה",
      "name": "רמת ורבר",
      "paidDate": "",
      "status": "unpaid",
      "execDate": "2026-05-19",
      "amount": 4000
    },
    {
      "id": "1700000016",
      "type": "expense",
      "name": "איתן",
      "execDate": "2025-09-16",
      "payDate": "2025-10-15",
      "amount": 0,
      "subAmounts": [],
      "status": "unpaid",
      "paidDate": "",
      "notes": "300"
    },
    {
      "payDate": "2026-05-15",
      "id": "1700000031",
      "type": "expense",
      "notes": "ח-ן 1020",
      "name": "גולד",
      "paidDate": "",
      "status": "unpaid",
      "execDate": "2026-04-20",
      "amount": 1770
    },
    {
      "payDate": "2026-05-15",
      "id": "1700000035",
      "type": "expense",
      "notes": "ח-ן 623",
      "name": "דניאל טהאן",
      "paidDate": "",
      "status": "unpaid",
      "execDate": "2026-04-15",
      "amount": 1180
    },
    {
      "payDate": "2026-05-15",
      "id": "1700000040",
      "type": "expense",
      "notes": "",
      "name": "דניאל סקסופון",
      "paidDate": "",
      "status": "unpaid",
      "execDate": "2026-04-23",
      "amount": 600
    },
    {
      "id": "1700000045",
      "type": "expense",
      "name": "מנשה",
      "execDate": "2026-09-09",
      "payDate": "",
      "amount": 2587,
      "subAmounts": [
        {
          "value": 2587,
          "note": ""
        }
      ],
      "status": "unpaid",
      "paidDate": "",
      "notes": "מקיף ה אשקלון בספטמבר - שולם לנו נשלם למנשה אחרי ההופעה"
    },
    {
      "id": "1782296615818",
      "type": "expense",
      "name": "מנשה",
      "execDate": "2026-06-14",
      "payDate": "",
      "amount": 1800,
      "subAmounts": [
        {
          "value": 1800,
          "note": ""
        }
      ],
      "status": "unpaid",
      "paidDate": "",
      "notes": "טביב - שולם לנו ביקשתי ממנשה שישלח ח-ן עסקה ע\"ס 3,237₪ (כפר אדומים וטביב)"
    },
    {
      "id": "1782297773541",
      "type": "income",
      "name": "סל תרבות מקיף י ראשל\"צ",
      "execDate": "2026-06-18",
      "payDate": "",
      "amount": 9581,
      "subAmounts": [],
      "status": "unpaid",
      "paidDate": "",
      "notes": "נשלחה חשבונית עסקה"
    },
    {
      "id": "exp_1782384973561_39",
      "type": "expense",
      "name": "ניב",
      "execDate": "2026-05-06",
      "payDate": "2026-05-15",
      "amount": 500,
      "notes": "",
      "status": "unpaid",
      "paidDate": ""
    },
    {
      "id": "exp_1782371477054_8",
      "type": "expense",
      "name": "מנשה",
      "execDate": "2026-05-06",
      "payDate": "2026-06-15",
      "amount": 1437,
      "notes": "יובלים עמק חפר - שולם לנו ביקשתי חשבונית עסקה ממנשה",
      "status": "unpaid",
      "paidDate": ""
    },
    {
      "id": "exp_1782371477190_38",
      "type": "expense",
      "name": "עמית",
      "execDate": "2026-05-06",
      "payDate": "2026-07-15",
      "amount": 708,
      "notes": "",
      "status": "unpaid",
      "paidDate": ""
    },
    {
      "id": "exp_1782384973532_17",
      "type": "expense",
      "name": "בוריס",
      "execDate": "2026-06-18",
      "payDate": "2026-07-15",
      "amount": 1770,
      "notes": "",
      "status": "unpaid",
      "paidDate": ""
    },
    {
      "id": "exp_1782371477172_34",
      "type": "expense",
      "name": "מנשה",
      "execDate": "2026-04-12",
      "payDate": "2026-07-15",
      "amount": 2587,
      "notes": "מקיף ט אשדוד - שולם לנו ביקשתי חשבונית עסקה ממנשה",
      "status": "unpaid",
      "paidDate": ""
    },
    {
      "id": "exp_1782384973577_44",
      "type": "expense",
      "name": "עומרי גיטרה",
      "execDate": "2026-06-16",
      "payDate": "2026-08-15",
      "amount": 0,
      "notes": "",
      "status": "unpaid",
      "paidDate": ""
    },
    {
      "id": "exp_1782384973513_9",
      "type": "expense",
      "name": "אריאל סקסופון",
      "execDate": "2026-06-16",
      "payDate": "2026-08-15",
      "amount": 600,
      "notes": "",
      "status": "unpaid",
      "paidDate": ""
    },
    {
      "id": "exp_1782384973527_16",
      "type": "expense",
      "name": "בוריס",
      "execDate": "2026-06-16",
      "payDate": "2026-08-15",
      "amount": 1770,
      "notes": "",
      "status": "unpaid",
      "paidDate": ""
    },
    {
      "id": "exp_1782384973545_23",
      "type": "expense",
      "name": "גיל",
      "execDate": "2026-06-18",
      "payDate": "2026-07-15",
      "amount": 585,
      "notes": "",
      "status": "unpaid",
      "paidDate": ""
    },
    {
      "id": "exp_9",
      "type": "expense",
      "name": "אנביטק",
      "execDate": "2025-10-15",
      "payDate": "2026-07-15",
      "amount": 414,
      "notes": "שולם",
      "status": "paid",
      "paidDate": "2026-06-17"
    },
    {
      "id": "exp_1782371477049_7",
      "type": "expense",
      "name": "עמית",
      "execDate": "2026-06-14",
      "payDate": "2026-08-15",
      "amount": 944,
      "notes": "",
      "status": "unpaid",
      "paidDate": ""
    },
    {
      "id": "exp_1782384973565_40",
      "type": "expense",
      "name": "ניב",
      "execDate": "2026-06-14",
      "payDate": "2026-05-15",
      "amount": 700,
      "notes": "",
      "status": "unpaid",
      "paidDate": ""
    },
    {
      "id": "exp_1782384973541_22",
      "type": "expense",
      "name": "גיל",
      "execDate": "2026-06-14",
      "payDate": "2026-08-15",
      "amount": 826,
      "notes": "",
      "status": "unpaid",
      "paidDate": ""
    },
    {
      "id": "exp_1782384973509_8",
      "type": "expense",
      "name": "אריאל סקסופון",
      "execDate": "2026-05-13",
      "payDate": "2026-07-15",
      "amount": 600,
      "notes": "שולם",
      "status": "paid_bit",
      "paidDate": ""
    },
    {
      "id": "exp_47",
      "type": "expense",
      "name": "שי ברק",
      "execDate": "2026-06-18",
      "payDate": "2026-08-15",
      "amount": 767,
      "notes": "",
      "status": "unpaid",
      "paidDate": ""
    },
    {
      "id": "exp_1782384973574_43",
      "type": "expense",
      "name": "עומרי גיטרה",
      "execDate": "2026-05-13",
      "payDate": "2026-07-15",
      "amount": 0,
      "notes": "שולם 500 בהעברה חסרה חשבונית",
      "status": "paid",
      "paidDate": ""
    },
    {
      "id": "exp_1782384973523_15",
      "type": "expense",
      "name": "בוריס",
      "execDate": "2026-05-13",
      "payDate": "2026-07-15",
      "amount": 1770,
      "notes": "",
      "status": "unpaid",
      "paidDate": ""
    },
    {
      "id": "exp_1782384973594_51",
      "type": "expense",
      "name": "רונן רחמני",
      "execDate": "2026-06-16",
      "payDate": "2026-08-15",
      "amount": 1416,
      "notes": "",
      "status": "unpaid",
      "paidDate": ""
    },
    {
      "id": "exp_1782384973538_21",
      "type": "expense",
      "name": "גיל",
      "execDate": "2026-05-06",
      "payDate": "2026-07-15",
      "amount": 585,
      "notes": "ח-ן 50087",
      "status": "paid_bit",
      "paidDate": ""
    },
    {
      "id": "exp_39",
      "type": "expense",
      "name": "עמית",
      "execDate": "2026-05-13",
      "payDate": "2026-07-15",
      "amount": 708,
      "notes": "",
      "status": "unpaid",
      "paidDate": ""
    },
    {
      "id": "exp_1782384973520_14",
      "type": "expense",
      "name": "בוריס",
      "execDate": "2026-05-06",
      "payDate": "2026-07-15",
      "amount": 1770,
      "notes": "",
      "status": "unpaid",
      "paidDate": ""
    },
    {
      "id": "exp_1782384973590_49",
      "type": "expense",
      "name": "עמית",
      "execDate": "2026-06-18",
      "payDate": "2026-08-15",
      "amount": 708,
      "notes": "",
      "status": "unpaid",
      "paidDate": ""
    },
    {
      "id": "exp_1782384973568_41",
      "type": "expense",
      "name": "ניב",
      "execDate": "2026-06-18",
      "payDate": "2026-05-15",
      "amount": 500,
      "notes": "",
      "status": "unpaid",
      "paidDate": ""
    },
    {
      "id": "exp_1782384973586_48",
      "type": "expense",
      "name": "עמית",
      "execDate": "2026-06-16",
      "payDate": "2026-08-15",
      "amount": 708,
      "notes": "",
      "status": "unpaid",
      "paidDate": ""
    },
    {
      "id": "exp_1782371477211_43",
      "type": "expense",
      "name": "מנשה",
      "execDate": "2026-09-14",
      "payDate": "2026-07-15",
      "amount": 1437,
      "notes": "",
      "status": "unpaid",
      "paidDate": ""
    },
    {
      "id": "exp_1782371477186_37",
      "type": "expense",
      "name": "מנשה",
      "execDate": "2026-04-23",
      "payDate": "",
      "amount": 1437,
      "notes": "כפר אדומים - שולם לנו ביקשתי ממנשה שישלח ח-ן עסקה ע\"ס 3,237₪ (כפר אדומים וטביב)",
      "status": "unpaid",
      "paidDate": ""
    },
    {
      "id": "exp_1782371477350_69",
      "type": "expense",
      "name": "שי ברק",
      "execDate": "2026-04-27",
      "payDate": "2026-07-15",
      "amount": 767,
      "notes": "ח-ן 60459",
      "status": "paid_paybox",
      "paidDate": ""
    },
    {
      "id": "exp_1782371477427_84",
      "type": "expense",
      "name": "סימון",
      "execDate": "2026-04-20",
      "payDate": "2026-05-15",
      "amount": 2006,
      "notes": "ח-ן 291",
      "status": "unpaid",
      "paidDate": ""
    },
    {
      "id": "exp_5",
      "type": "expense",
      "name": "איתן",
      "execDate": "2025-10-15",
      "payDate": "2025-11-15",
      "amount": 0,
      "notes": 500,
      "status": "unpaid",
      "paidDate": ""
    },
    {
      "id": "inc_1782371476272_10",
      "type": "income",
      "name": "שימקוטק",
      "execDate": "2026-04-26",
      "payDate": "2026-06-30",
      "amount": 1174,
      "notes": "",
      "status": "unpaid",
      "paidDate": ""
    },
    {
      "id": "inc_1782371476289_14",
      "type": "income",
      "name": "דרור רימוק",
      "execDate": "2026-03-09",
      "payDate": "",
      "amount": 732,
      "notes": "ESET?",
      "status": "unpaid",
      "paidDate": ""
    },
    {
      "id": "exp_1782371477400_79",
      "type": "expense",
      "name": "קומסקיור",
      "execDate": "2026-05-07",
      "payDate": "2026-08-15",
      "amount": 1389,
      "notes": "",
      "status": "unpaid",
      "paidDate": ""
    },
    {
      "id": "exp_12",
      "type": "expense",
      "name": "בוריס",
      "execDate": "2026-04-21",
      "payDate": "2026-05-15",
      "amount": 1770,
      "notes": "יש חשבונית",
      "status": "paid_paybox",
      "paidDate": ""
    },
    {
      "id": "inc_1782371476225_2",
      "type": "income",
      "name": "מסע ישראלי חמד שפיר",
      "execDate": "2026-05-13",
      "payDate": "2026-07-11",
      "amount": 9581,
      "notes": "נשלחה חשבונית עסקה",
      "status": "unpaid",
      "paidDate": ""
    },
    {
      "id": "inc_1782371476244_6",
      "type": "income",
      "name": "קרן כספית",
      "execDate": "2025-12-25",
      "payDate": "",
      "amount": 0,
      "notes": "",
      "status": "unpaid",
      "paidDate": ""
    },
    {
      "id": "exp_1782371477451_88",
      "type": "expense",
      "name": "בוריס",
      "execDate": "2026-04-12",
      "payDate": "2026-05-15",
      "amount": 1770,
      "notes": "יש חשבונית",
      "status": "paid_paybox",
      "paidDate": ""
    },
    {
      "id": "exp_1782371477107_20",
      "type": "expense",
      "name": "דניאל טהאן",
      "execDate": "2026-04-21",
      "payDate": "2026-07-15",
      "amount": 1227,
      "notes": "ח-ן 623",
      "status": "paid_bit",
      "paidDate": ""
    },
    {
      "id": "exp_1782371477304_60",
      "type": "expense",
      "name": "דניאל טהאן",
      "execDate": "2026-04-12",
      "payDate": "2026-07-15",
      "amount": 1227,
      "notes": "ח-ן 623",
      "status": "paid_bit",
      "paidDate": ""
    },
    {
      "id": "exp_1782371477329_65",
      "type": "expense",
      "name": "איתן",
      "execDate": "2025-09-01",
      "payDate": "2025-10-15",
      "amount": 0,
      "notes": 800,
      "status": "unpaid",
      "paidDate": ""
    },
    {
      "id": "exp_22",
      "type": "expense",
      "name": "דניאל טהאן",
      "execDate": "2026-05-13",
      "payDate": "2026-06-15",
      "amount": 944,
      "notes": "ח-ן 629 ע\"ס 2124",
      "status": "unpaid",
      "paidDate": ""
    },
    {
      "id": "exp_14",
      "type": "expense",
      "name": "בוריס",
      "execDate": "2026-04-27",
      "payDate": "2026-05-15",
      "amount": 1770,
      "notes": "יש חשבונית",
      "status": "paid_paybox",
      "paidDate": ""
    },
    {
      "id": "exp_33",
      "type": "expense",
      "name": "ניב",
      "execDate": "2026-04-12",
      "payDate": "2026-05-15",
      "amount": 800,
      "notes": "",
      "status": "unpaid",
      "paidDate": ""
    },
    {
      "id": "exp_21",
      "type": "expense",
      "name": "דניאל טהאן",
      "execDate": "2026-05-06",
      "payDate": "2026-06-15",
      "amount": 1180,
      "notes": "ח-ן 629 ע\"ס 2124",
      "status": "unpaid",
      "paidDate": ""
    },
    {
      "id": "exp_1782371477215_44",
      "type": "expense",
      "name": "דניאל טהאן",
      "execDate": "2026-05-19",
      "payDate": "2026-06-15",
      "amount": 944,
      "notes": "ח-ן 944",
      "status": "unpaid",
      "paidDate": ""
    },
    {
      "id": "exp_1782384973498_0",
      "type": "expense",
      "name": "אדוארד הגברה",
      "execDate": "",
      "payDate": "",
      "amount": 1180,
      "notes": "",
      "status": "unpaid",
      "paidDate": ""
    },
    {
      "id": "exp_1782371477116_22",
      "type": "expense",
      "name": "גיל",
      "execDate": "2026-02-13",
      "payDate": "2026-07-15",
      "amount": 944,
      "notes": "ח-ן 50087",
      "status": "paid_bit",
      "paidDate": ""
    },
    {
      "id": "exp_17",
      "type": "expense",
      "name": "גיל",
      "execDate": "2026-04-12",
      "payDate": "2026-07-15",
      "amount": 944,
      "notes": "ח-ן 50087",
      "status": "paid_bit",
      "paidDate": ""
    },
    {
      "id": "exp_13",
      "type": "expense",
      "name": "בוריס",
      "execDate": "2026-04-23",
      "payDate": "2026-05-15",
      "amount": 1970,
      "notes": "יש חשבונית",
      "status": "paid_paybox",
      "paidDate": ""
    },
    {
      "id": "exp_1782384973597_52",
      "type": "expense",
      "name": "שי ברק",
      "execDate": "2026-04-23",
      "payDate": "2026-07-15",
      "amount": 767,
      "notes": "ח-ן 60459",
      "status": "paid_paybox",
      "paidDate": ""
    },
    {
      "id": "exp_1782384973505_6",
      "type": "expense",
      "name": "איתן",
      "execDate": "2025-09-08",
      "payDate": "2025-10-15",
      "amount": 0,
      "notes": 500,
      "status": "unpaid",
      "paidDate": ""
    },
    {
      "id": "exp_1782371477206_42",
      "type": "expense",
      "name": "איתן",
      "execDate": "2025-09-04",
      "payDate": "2025-10-15",
      "amount": 0,
      "notes": 800,
      "status": "unpaid",
      "paidDate": ""
    },
    {
      "id": "exp_1782371477181_36",
      "type": "expense",
      "name": "איתן",
      "execDate": "2025-09-18",
      "payDate": "2025-10-15",
      "amount": 0,
      "notes": 500,
      "status": "unpaid",
      "paidDate": ""
    },
    {
      "id": "exp_1782371477253_51",
      "type": "expense",
      "name": "מנשה",
      "execDate": "2026-09-09",
      "payDate": "",
      "amount": 2586.6,
      "notes": "מקיף ה אשקלון בספטמבר",
      "status": "unpaid",
      "paidDate": ""
    },
    {
      "id": "inc_1782371476214_0",
      "type": "income",
      "name": "מנו",
      "execDate": "2026-04-27",
      "payDate": "",
      "amount": 649,
      "notes": "תמיכה מרחוק+אתר לקוח",
      "status": "unpaid",
      "paidDate": ""
    },
    {
      "id": "show_18_0_1782408869930",
      "type": "expense",
      "name": "אדוארד – הגברה",
      "execDate": "2026-06-14",
      "payDate": "",
      "amount": 0,
      "status": "unpaid",
      "paidDate": "",
      "notes": "מופע חטיבת טביב ראשון לציון 14/06/26"
    },
    {
      "id": "show_18_1_1782408869930",
      "type": "expense",
      "name": "עמית כהן",
      "execDate": "2026-06-14",
      "payDate": "",
      "amount": 0,
      "status": "unpaid",
      "paidDate": "",
      "notes": "מופע חטיבת טביב ראשון לציון 14/06/26"
    },
    {
      "id": "show_18_2_1782408869930",
      "type": "expense",
      "name": "ניב רז",
      "execDate": "2026-06-14",
      "payDate": "",
      "amount": 0,
      "status": "unpaid",
      "paidDate": "",
      "notes": "מופע חטיבת טביב ראשון לציון 14/06/26"
    },
    {
      "id": "show_18_3_1782408869930",
      "type": "expense",
      "name": "סקסופון - גיל סמואל",
      "execDate": "2026-06-14",
      "payDate": "",
      "amount": 0,
      "status": "unpaid",
      "paidDate": "",
      "notes": "מופע חטיבת טביב ראשון לציון 14/06/26"
    },
    {
      "id": "show_18_4_1782408869930",
      "type": "expense",
      "name": "קלידן - נתי באן",
      "execDate": "2026-06-14",
      "payDate": "",
      "amount": 0,
      "status": "unpaid",
      "paidDate": "",
      "notes": "מופע חטיבת טביב ראשון לציון 14/06/26"
    },
    {
      "id": "show_18_5_1782408869930",
      "type": "expense",
      "name": "בוריס – הגברה",
      "execDate": "2026-06-14",
      "payDate": "",
      "amount": 0,
      "status": "unpaid",
      "paidDate": "",
      "notes": "מופע חטיבת טביב ראשון לציון 14/06/26"
    },
    {
      "id": "show_19_0_1782408869930",
      "type": "expense",
      "name": "בוריס – הגברה",
      "execDate": "2026-06-16",
      "payDate": "",
      "amount": 0,
      "status": "unpaid",
      "paidDate": "",
      "notes": "מופע צור הדסה 16/06/26"
    },
    {
      "id": "show_19_1_1782408869930",
      "type": "expense",
      "name": "עמית כהן",
      "execDate": "2026-06-16",
      "payDate": "",
      "amount": 0,
      "status": "unpaid",
      "paidDate": "",
      "notes": "מופע צור הדסה 16/06/26"
    },
    {
      "id": "show_19_2_1782408869930",
      "type": "expense",
      "name": "עומרי - גיטרה",
      "execDate": "2026-06-16",
      "payDate": "",
      "amount": 0,
      "status": "unpaid",
      "paidDate": "",
      "notes": "מופע צור הדסה 16/06/26"
    },
    {
      "id": "show_19_3_1782408869930",
      "type": "expense",
      "name": "רונן רחמני",
      "execDate": "2026-06-16",
      "payDate": "",
      "amount": 0,
      "status": "unpaid",
      "paidDate": "",
      "notes": "מופע צור הדסה 16/06/26"
    },
    {
      "id": "show_19_4_1782408869930",
      "type": "expense",
      "name": "סקסופון - אריאל אשקלון",
      "execDate": "2026-06-16",
      "payDate": "",
      "amount": 0,
      "status": "unpaid",
      "paidDate": "",
      "notes": "מופע צור הדסה 16/06/26"
    },
    {
      "id": "show_20_0_1782408869930",
      "type": "expense",
      "name": "בוריס – הגברה",
      "execDate": "2026-06-18",
      "payDate": "",
      "amount": 0,
      "status": "unpaid",
      "paidDate": "",
      "notes": "מופע מקיף י ראשלצ 18/06/26"
    },
    {
      "id": "show_20_1_1782408869930",
      "type": "expense",
      "name": "שי ברק",
      "execDate": "2026-06-18",
      "payDate": "",
      "amount": 0,
      "status": "unpaid",
      "paidDate": "",
      "notes": "מופע מקיף י ראשלצ 18/06/26"
    },
    {
      "id": "show_20_2_1782408869930",
      "type": "expense",
      "name": "עמית כהן",
      "execDate": "2026-06-18",
      "payDate": "",
      "amount": 0,
      "status": "unpaid",
      "paidDate": "",
      "notes": "מופע מקיף י ראשלצ 18/06/26"
    },
    {
      "id": "show_20_3_1782408869930",
      "type": "expense",
      "name": "ניב רז",
      "execDate": "2026-06-18",
      "payDate": "",
      "amount": 0,
      "status": "unpaid",
      "paidDate": "",
      "notes": "מופע מקיף י ראשלצ 18/06/26"
    },
    {
      "id": "show_20_4_1782408869930",
      "type": "expense",
      "name": "סקסופון - גיל סמואל",
      "execDate": "2026-06-18",
      "payDate": "",
      "amount": 0,
      "status": "unpaid",
      "paidDate": "",
      "notes": "מופע מקיף י ראשלצ 18/06/26"
    },
    {
      "id": "show_income_1_1782409764812",
      "type": "income",
      "name": "ירושלים אנחנו",
      "execDate": "2025-11-20",
      "payDate": "",
      "amount": 0,
      "status": "unpaid",
      "paidDate": "",
      "notes": "מופע 20/11/25"
    },
    {
      "id": "show_income_2_1782409764812",
      "type": "income",
      "name": "מודיעין מנשה אמיר",
      "execDate": "2025-12-15",
      "payDate": "",
      "amount": 0,
      "status": "unpaid",
      "paidDate": "",
      "notes": "מופע 15/12/25"
    },
    {
      "id": "show_presenter_2_1782409764812",
      "type": "expense",
      "name": "מנשה אמיר",
      "execDate": "2025-12-15",
      "payDate": "",
      "amount": 0,
      "status": "unpaid",
      "paidDate": "",
      "notes": "מופע מודיעין 15/12/25"
    },
    {
      "id": "show_income_3_1782409764812",
      "type": "income",
      "name": "ראשון לציון מנשה אמיר",
      "execDate": "2026-01-27",
      "payDate": "",
      "amount": 0,
      "status": "unpaid",
      "paidDate": "",
      "notes": "מופע 27/01/26"
    },
    {
      "id": "show_presenter_3_1782409764812",
      "type": "expense",
      "name": "מנשה אמיר",
      "execDate": "2026-01-27",
      "payDate": "",
      "amount": 0,
      "status": "unpaid",
      "paidDate": "",
      "notes": "מופע ראשון לציון 27/01/26"
    },
    {
      "id": "show_income_4_1782409764812",
      "type": "income",
      "name": "שקמים הוד השרון מנשה אמיר",
      "execDate": "2026-02-08",
      "payDate": "",
      "amount": 0,
      "status": "unpaid",
      "paidDate": "",
      "notes": "מופע 08/02/26"
    },
    {
      "id": "show_presenter_4_1782409764812",
      "type": "expense",
      "name": "מנשה אמיר",
      "execDate": "2026-02-08",
      "payDate": "",
      "amount": 0,
      "status": "unpaid",
      "paidDate": "",
      "notes": "מופע שקמים הוד השרון 08/02/26"
    },
    {
      "id": "show_income_5_1782409764812",
      "type": "income",
      "name": "תל מונד אנחנו",
      "execDate": "2026-02-11",
      "payDate": "",
      "amount": 0,
      "status": "unpaid",
      "paidDate": "",
      "notes": "מופע 11/02/26"
    },
    {
      "id": "show_income_6_1782409764812",
      "type": "income",
      "name": "הנשיא בת ים מנשה אמיר",
      "execDate": "2026-02-13",
      "payDate": "",
      "amount": 0,
      "status": "unpaid",
      "paidDate": "",
      "notes": "מופע 13/02/26"
    },
    {
      "id": "show_presenter_6_1782409764812",
      "type": "expense",
      "name": "מנשה אמיר",
      "execDate": "2026-02-13",
      "payDate": "",
      "amount": 0,
      "status": "unpaid",
      "paidDate": "",
      "notes": "מופע הנשיא בת ים 13/02/26"
    },
    {
      "id": "show_income_7_1782409764812",
      "type": "income",
      "name": "נהרייה מנשה אמיר",
      "execDate": "2026-02-17",
      "payDate": "",
      "amount": 0,
      "status": "unpaid",
      "paidDate": "",
      "notes": "מופע 17/02/26"
    },
    {
      "id": "show_presenter_7_1782409764812",
      "type": "expense",
      "name": "מנשה אמיר",
      "execDate": "2026-02-17",
      "payDate": "",
      "amount": 0,
      "status": "unpaid",
      "paidDate": "",
      "notes": "מופע נהרייה 17/02/26"
    },
    {
      "id": "show_income_8_1782409764812",
      "type": "income",
      "name": "פתח תקווה אנחנו",
      "execDate": "2026-03-10",
      "payDate": "",
      "amount": 0,
      "status": "unpaid",
      "paidDate": "",
      "notes": "מופע 10/03/26"
    },
    {
      "id": "show_income_9_1782409764812",
      "type": "income",
      "name": "מקיף ט אשדוד מנשה אמיר",
      "execDate": "2026-04-12",
      "payDate": "",
      "amount": 0,
      "status": "unpaid",
      "paidDate": "",
      "notes": "מופע 12/04/26"
    },
    {
      "id": "show_presenter_9_1782409764812",
      "type": "expense",
      "name": "מנשה אמיר",
      "execDate": "2026-04-12",
      "payDate": "",
      "amount": 0,
      "status": "unpaid",
      "paidDate": "",
      "notes": "מופע מקיף ט אשדוד 12/04/26"
    },
    {
      "id": "show_income_10_1782409764812",
      "type": "income",
      "name": "רמת גן אנחנו",
      "execDate": "2026-04-15",
      "payDate": "",
      "amount": 0,
      "status": "unpaid",
      "paidDate": "",
      "notes": "מופע 15/04/26"
    },
    {
      "id": "show_income_11_1782409764812",
      "type": "income",
      "name": "אורט רמות ים אנחנו ?",
      "execDate": "2026-04-16",
      "payDate": "",
      "amount": 0,
      "status": "unpaid",
      "paidDate": "",
      "notes": "מופע 16/04/26"
    },
    {
      "id": "show_income_12_1782409764812",
      "type": "income",
      "name": "עירוני ד' חגי שניר",
      "execDate": "2026-04-21",
      "payDate": "",
      "amount": 0,
      "status": "unpaid",
      "paidDate": "",
      "notes": "מופע 21/04/26"
    },
    {
      "id": "show_income_13_1782409764812",
      "type": "income",
      "name": "מעיינות כפר אדומים מנשה אמיר",
      "execDate": "2026-04-23",
      "payDate": "",
      "amount": 0,
      "status": "unpaid",
      "paidDate": "",
      "notes": "מופע 23/04/26"
    },
    {
      "id": "show_presenter_13_1782409764812",
      "type": "expense",
      "name": "מנשה אמיר",
      "execDate": "2026-04-23",
      "payDate": "",
      "amount": 0,
      "status": "unpaid",
      "paidDate": "",
      "notes": "מופע מעיינות כפר אדומים 23/04/26"
    },
    {
      "id": "show_income_14_1782409764812",
      "type": "income",
      "name": "הדר כפר יונה אנחנו",
      "execDate": "2026-04-27",
      "payDate": "",
      "amount": 0,
      "status": "unpaid",
      "paidDate": "",
      "notes": "מופע 27/04/26"
    },
    {
      "id": "show_income_15_1782409764812",
      "type": "income",
      "name": "עמק חפר מנשה אמיר",
      "execDate": "2026-05-11",
      "payDate": "",
      "amount": 0,
      "status": "unpaid",
      "paidDate": "",
      "notes": "מופע 11/05/26"
    },
    {
      "id": "show_presenter_15_1782409764812",
      "type": "expense",
      "name": "מנשה אמיר",
      "execDate": "2026-05-11",
      "payDate": "",
      "amount": 0,
      "status": "unpaid",
      "paidDate": "",
      "notes": "מופע עמק חפר 11/05/26"
    },
    {
      "id": "show_income_16_1782409764812",
      "type": "income",
      "name": "ממד חמד שפיר אנחנו",
      "execDate": "2026-05-13",
      "payDate": "",
      "amount": 0,
      "status": "unpaid",
      "paidDate": "",
      "notes": "מופע 13/05/26"
    },
    {
      "id": "show_income_17_1782409764812",
      "type": "income",
      "name": "פתח תקווה אנחנו",
      "execDate": "2026-05-19",
      "payDate": "",
      "amount": 0,
      "status": "unpaid",
      "paidDate": "",
      "notes": "מופע 19/05/26"
    }
  ],
  "bankBalance": "55014",
  "savedAt": "2026-06-25T11:43:25.479Z"
}